pyretrosheet/__init__.py
pyretrosheet/load.py
pyretrosheet/retrosheet.py
pyretrosheet/models/__init__.py
pyretrosheet/models/base.py
pyretrosheet/models/exceptions.py
pyretrosheet/models/game.py
pyretrosheet/models/game_id.py
pyretrosheet/models/player.py
pyretrosheet/models/team.py
pyretrosheet/models/play/__init__.py
pyretrosheet/models/play/advance.py
pyretrosheet/models/play/description.py
pyretrosheet/models/play/event.py
pyretrosheet/models/play/ignored.py
pyretrosheet/models/play/modifier.py
pyretrosheet/views/__init__.py
pyretrosheet-0.0.10.dist-info/LICENSE
pyretrosheet-0.0.10.dist-info/WHEEL
pyretrosheet-0.0.10.dist-info/METADATA
pyretrosheet-0.0.10.dist-info/RECORD
