Metadata-Version: 2.1
Name: pyretrosheet
Version: 0.0.10
Summary: Load, analyze, and enrich retrosheet.org MLB data.
Author-email: Ryan Ozelie <ryan.ozelie@gmail.com>
Requires-Python: >=3.11
Classifier: Programming Language :: Python :: 3.11
Classifier: License :: OSI Approved :: MIT License
Classifier: Operating System :: OS Independent
Requires-Dist: requests>=2.31.0,<3
Requires-Dist: pytest==7.4.3 ; extra == "dev"
Requires-Dist: black==23.11.0 ; extra == "dev"
Requires-Dist: isort==5.12.0 ; extra == "dev"
Requires-Dist: mypy==1.7.1 ; extra == "dev"
Requires-Dist: ruff==0.1.6 ; extra == "dev"
Requires-Dist: types-requests>=2.31.0,<3 ; extra == "dev"
Requires-Dist: requests-mock==1.11.0 ; extra == "dev"
Requires-Dist: pytest-mock==3.12.0 ; extra == "dev"
Requires-Dist: coverage==7.3.2 ; extra == "dev"
Requires-Dist: pytest-xdist==3.5.0 ; extra == "dev"
Project-URL: Homepage, https://github.com/rozelie/pyretrosheet
Provides-Extra: dev
